{
  "basic": {
    "title": "Design Bounded Blocking Queue",
    "titleSlug": "design-bounded-blocking-queue",
    "frontendQuestionId": 1209,
    "acRate": null,
    "difficulty": {
      "level": 2
    },
    "paidOnly": true,
    "isFavor": false,
    "status": null
  },
  "detail": {
    "questionId": "1209",
    "title": "Design Bounded Blocking Queue",
    "titleSlug": "design-bounded-blocking-queue",
    "content": null,
    "difficulty": "Medium",
    "likes": 540,
    "dislikes": 43,
    "isPaidOnly": true,
    "sampleTestCase": "1\n1\n[\"BoundedBlockingQueue\",\"enqueue\",\"dequeue\",\"dequeue\",\"enqueue\",\"enqueue\",\"enqueue\",\"enqueue\",\"dequeue\"]\n[[2],[1],[],[],[0],[2],[3],[4],[]]",
    "codeSnippets": null,
    "topicTags": [
      {
        "name": "Concurrency",
        "slug": "concurrency",
        "translatedName": null
      }
    ],
    "stats": "{\"totalAccepted\": \"64.8K\", \"totalSubmission\": \"88.3K\", \"totalAcceptedRaw\": 64765, \"totalSubmissionRaw\": 88306, \"acRate\": \"73.3%\"}",
    "similarQuestions": "[]",
    "stats_parsed": {
      "totalAccepted": "64.8K",
      "totalSubmission": "88.3K",
      "totalAcceptedRaw": 64765,
      "totalSubmissionRaw": 88306,
      "acRate": "73.3%"
    },
    "similarQuestions_parsed": []
  },
  "discussions_preview": [],
  "fetched_at": "2025-11-25T14:57:13.678988Z"
}