{
  "basic": {
    "title": "Find Customers With Positive Revenue this Year",
    "titleSlug": "find-customers-with-positive-revenue-this-year",
    "frontendQuestionId": 1974,
    "acRate": null,
    "difficulty": {
      "level": 1
    },
    "paidOnly": true,
    "isFavor": false,
    "status": null
  },
  "detail": {
    "questionId": "1974",
    "title": "Find Customers With Positive Revenue this Year",
    "titleSlug": "find-customers-with-positive-revenue-this-year",
    "content": null,
    "difficulty": "Easy",
    "likes": 66,
    "dislikes": 25,
    "isPaidOnly": true,
    "sampleTestCase": "{\"headers\":{\"Customers\":[\"customer_id\",\"year\",\"revenue\"]},\"rows\":{\"Customers\":[[\"1\",\"2018\",\"50\"],[\"1\",\"2021\",\"30\"],[\"1\",\"2020\",\"70\"],[\"2\",\"2021\",\"-50\"],[\"3\",\"2018\",\"10\"],[\"3\",\"2016\",\"50\"],[\"4\",\"2021\",\"20\"]]}}",
    "codeSnippets": null,
    "topicTags": [
      {
        "name": "Database",
        "slug": "database",
        "translatedName": null
      }
    ],
    "stats": "{\"totalAccepted\": \"35.3K\", \"totalSubmission\": \"40.3K\", \"totalAcceptedRaw\": 35286, \"totalSubmissionRaw\": 40259, \"acRate\": \"87.6%\"}",
    "similarQuestions": "[]",
    "stats_parsed": {
      "totalAccepted": "35.3K",
      "totalSubmission": "40.3K",
      "totalAcceptedRaw": 35286,
      "totalSubmissionRaw": 40259,
      "acRate": "87.6%"
    },
    "similarQuestions_parsed": []
  },
  "discussions_preview": [],
  "fetched_at": "2025-11-25T14:57:13.678988Z"
}