{
  "basic": {
    "title": "Largest BST Subtree",
    "titleSlug": "largest-bst-subtree",
    "frontendQuestionId": 333,
    "acRate": null,
    "difficulty": {
      "level": 2
    },
    "paidOnly": true,
    "isFavor": false,
    "status": null
  },
  "detail": {
    "questionId": "333",
    "title": "Largest BST Subtree",
    "titleSlug": "largest-bst-subtree",
    "content": null,
    "difficulty": "Medium",
    "likes": 1563,
    "dislikes": 147,
    "isPaidOnly": true,
    "sampleTestCase": "[10,5,15,1,8,null,7]",
    "codeSnippets": null,
    "topicTags": [
      {
        "name": "Dynamic Programming",
        "slug": "dynamic-programming",
        "translatedName": null
      },
      {
        "name": "Tree",
        "slug": "tree",
        "translatedName": null
      },
      {
        "name": "Depth-First Search",
        "slug": "depth-first-search",
        "translatedName": null
      },
      {
        "name": "Binary Search Tree",
        "slug": "binary-search-tree",
        "translatedName": null
      },
      {
        "name": "Binary Tree",
        "slug": "binary-tree",
        "translatedName": null
      }
    ],
    "stats": "{\"totalAccepted\": \"127.3K\", \"totalSubmission\": \"278.3K\", \"totalAcceptedRaw\": 127292, \"totalSubmissionRaw\": 278310, \"acRate\": \"45.7%\"}",
    "similarQuestions": "[]",
    "stats_parsed": {
      "totalAccepted": "127.3K",
      "totalSubmission": "278.3K",
      "totalAcceptedRaw": 127292,
      "totalSubmissionRaw": 278310,
      "acRate": "45.7%"
    },
    "similarQuestions_parsed": []
  },
  "discussions_preview": [],
  "fetched_at": "2025-11-25T14:57:13.678988Z"
}