{
  "basic": {
    "title": "Minimum Swaps to Group All 1's Together",
    "titleSlug": "minimum-swaps-to-group-all-1s-together",
    "frontendQuestionId": 1107,
    "acRate": null,
    "difficulty": {
      "level": 2
    },
    "paidOnly": true,
    "isFavor": false,
    "status": null
  },
  "detail": {
    "questionId": "1107",
    "title": "Minimum Swaps to Group All 1's Together",
    "titleSlug": "minimum-swaps-to-group-all-1s-together",
    "content": null,
    "difficulty": "Medium",
    "likes": 1271,
    "dislikes": 18,
    "isPaidOnly": true,
    "sampleTestCase": "[1,0,1,0,1]",
    "codeSnippets": null,
    "topicTags": [
      {
        "name": "Array",
        "slug": "array",
        "translatedName": null
      },
      {
        "name": "Sliding Window",
        "slug": "sliding-window",
        "translatedName": null
      }
    ],
    "stats": "{\"totalAccepted\": \"87.6K\", \"totalSubmission\": \"143.2K\", \"totalAcceptedRaw\": 87557, \"totalSubmissionRaw\": 143181, \"acRate\": \"61.2%\"}",
    "similarQuestions": "[{\"title\": \"Minimum Adjacent Swaps for K Consecutive Ones\", \"titleSlug\": \"minimum-adjacent-swaps-for-k-consecutive-ones\", \"difficulty\": \"Hard\", \"translatedTitle\": null}, {\"title\": \"Minimum Swaps to Group All 1's Together II\", \"titleSlug\": \"minimum-swaps-to-group-all-1s-together-ii\", \"difficulty\": \"Medium\", \"translatedTitle\": null}, {\"title\": \"Time Needed to Rearrange a Binary String\", \"titleSlug\": \"time-needed-to-rearrange-a-binary-string\", \"difficulty\": \"Medium\", \"translatedTitle\": null}, {\"title\": \"Minimum Moves to Pick K Ones\", \"titleSlug\": \"minimum-moves-to-pick-k-ones\", \"difficulty\": \"Hard\", \"translatedTitle\": null}]",
    "stats_parsed": {
      "totalAccepted": "87.6K",
      "totalSubmission": "143.2K",
      "totalAcceptedRaw": 87557,
      "totalSubmissionRaw": 143181,
      "acRate": "61.2%"
    },
    "similarQuestions_parsed": [
      {
        "title": "Minimum Adjacent Swaps for K Consecutive Ones",
        "titleSlug": "minimum-adjacent-swaps-for-k-consecutive-ones",
        "difficulty": "Hard",
        "translatedTitle": null
      },
      {
        "title": "Minimum Swaps to Group All 1's Together II",
        "titleSlug": "minimum-swaps-to-group-all-1s-together-ii",
        "difficulty": "Medium",
        "translatedTitle": null
      },
      {
        "title": "Time Needed to Rearrange a Binary String",
        "titleSlug": "time-needed-to-rearrange-a-binary-string",
        "difficulty": "Medium",
        "translatedTitle": null
      },
      {
        "title": "Minimum Moves to Pick K Ones",
        "titleSlug": "minimum-moves-to-pick-k-ones",
        "difficulty": "Hard",
        "translatedTitle": null
      }
    ]
  },
  "discussions_preview": [],
  "fetched_at": "2025-11-25T14:57:13.678988Z"
}