{
  "basic": {
    "title": "Minimum Cost to Buy Apples",
    "titleSlug": "minimum-cost-to-buy-apples",
    "frontendQuestionId": 2612,
    "acRate": null,
    "difficulty": {
      "level": 2
    },
    "paidOnly": true,
    "isFavor": false,
    "status": null
  },
  "detail": {
    "questionId": "2612",
    "title": "Minimum Cost to Buy Apples",
    "titleSlug": "minimum-cost-to-buy-apples",
    "content": null,
    "difficulty": "Medium",
    "likes": 117,
    "dislikes": 27,
    "isPaidOnly": true,
    "sampleTestCase": "4\n[[1,2,4],[2,3,2],[2,4,5],[3,4,1],[1,3,4]]\n[56,42,102,301]\n2",
    "codeSnippets": null,
    "topicTags": [
      {
        "name": "Array",
        "slug": "array",
        "translatedName": null
      },
      {
        "name": "Graph",
        "slug": "graph",
        "translatedName": null
      },
      {
        "name": "Heap (Priority Queue)",
        "slug": "heap-priority-queue",
        "translatedName": null
      },
      {
        "name": "Shortest Path",
        "slug": "shortest-path",
        "translatedName": null
      }
    ],
    "stats": "{\"totalAccepted\": \"7.1K\", \"totalSubmission\": \"10.6K\", \"totalAcceptedRaw\": 7144, \"totalSubmissionRaw\": 10637, \"acRate\": \"67.2%\"}",
    "similarQuestions": "[]",
    "stats_parsed": {
      "totalAccepted": "7.1K",
      "totalSubmission": "10.6K",
      "totalAcceptedRaw": 7144,
      "totalSubmissionRaw": 10637,
      "acRate": "67.2%"
    },
    "similarQuestions_parsed": []
  },
  "discussions_preview": [],
  "fetched_at": "2025-11-25T14:57:13.678988Z"
}