{
  "basic": {
    "title": "Sentence Similarity",
    "titleSlug": "sentence-similarity",
    "frontendQuestionId": 734,
    "acRate": null,
    "difficulty": {
      "level": 1
    },
    "paidOnly": true,
    "isFavor": false,
    "status": null
  },
  "detail": {
    "questionId": "734",
    "title": "Sentence Similarity",
    "titleSlug": "sentence-similarity",
    "content": null,
    "difficulty": "Easy",
    "likes": 67,
    "dislikes": 72,
    "isPaidOnly": true,
    "sampleTestCase": "[\"great\",\"acting\",\"skills\"]\n[\"fine\",\"drama\",\"talent\"]\n[[\"great\",\"fine\"],[\"drama\",\"acting\"],[\"skills\",\"talent\"]]",
    "codeSnippets": null,
    "topicTags": [
      {
        "name": "Array",
        "slug": "array",
        "translatedName": null
      },
      {
        "name": "Hash Table",
        "slug": "hash-table",
        "translatedName": null
      },
      {
        "name": "String",
        "slug": "string",
        "translatedName": null
      }
    ],
    "stats": "{\"totalAccepted\": \"74K\", \"totalSubmission\": \"165.7K\", \"totalAcceptedRaw\": 74044, \"totalSubmissionRaw\": 165707, \"acRate\": \"44.7%\"}",
    "similarQuestions": "[{\"title\": \"Number of Provinces\", \"titleSlug\": \"number-of-provinces\", \"difficulty\": \"Medium\", \"translatedTitle\": null}, {\"title\": \"Accounts Merge\", \"titleSlug\": \"accounts-merge\", \"difficulty\": \"Medium\", \"translatedTitle\": null}, {\"title\": \"Sentence Similarity II\", \"titleSlug\": \"sentence-similarity-ii\", \"difficulty\": \"Medium\", \"translatedTitle\": null}]",
    "stats_parsed": {
      "totalAccepted": "74K",
      "totalSubmission": "165.7K",
      "totalAcceptedRaw": 74044,
      "totalSubmissionRaw": 165707,
      "acRate": "44.7%"
    },
    "similarQuestions_parsed": [
      {
        "title": "Number of Provinces",
        "titleSlug": "number-of-provinces",
        "difficulty": "Medium",
        "translatedTitle": null
      },
      {
        "title": "Accounts Merge",
        "titleSlug": "accounts-merge",
        "difficulty": "Medium",
        "translatedTitle": null
      },
      {
        "title": "Sentence Similarity II",
        "titleSlug": "sentence-similarity-ii",
        "difficulty": "Medium",
        "translatedTitle": null
      }
    ]
  },
  "discussions_preview": [],
  "fetched_at": "2025-11-25T14:57:13.678988Z"
}