{
  "basic": {
    "title": "Shortest Palindrome",
    "titleSlug": "shortest-palindrome",
    "frontendQuestionId": 214,
    "acRate": null,
    "difficulty": {
      "level": 3
    },
    "paidOnly": false,
    "isFavor": false,
    "status": null
  },
  "detail": {
    "questionId": "214",
    "title": "Shortest Palindrome",
    "titleSlug": "shortest-palindrome",
    "content": "<p>You are given a string <code>s</code>. You can convert <code>s</code> to a <span data-keyword=\"palindrome-string\">palindrome</span> by adding characters in front of it.</p>\n\n<p>Return <em>the shortest palindrome you can find by performing this transformation</em>.</p>\n\n<p>&nbsp;</p>\n<p><strong class=\"example\">Example 1:</strong></p>\n<pre><strong>Input:</strong> s = \"aacecaaa\"\n<strong>Output:</strong> \"aaacecaaa\"\n</pre><p><strong class=\"example\">Example 2:</strong></p>\n<pre><strong>Input:</strong> s = \"abcd\"\n<strong>Output:</strong> \"dcbabcd\"\n</pre>\n<p>&nbsp;</p>\n<p><strong>Constraints:</strong></p>\n\n<ul>\n\t<li><code>0 &lt;= s.length &lt;= 5 * 10<sup>4</sup></code></li>\n\t<li><code>s</code> consists of lowercase English letters only.</li>\n</ul>\n",
    "difficulty": "Hard",
    "likes": 4496,
    "dislikes": 289,
    "isPaidOnly": false,
    "sampleTestCase": "\"aacecaaa\"",
    "codeSnippets": [
      {
        "lang": "C++",
        "langSlug": "cpp",
        "code": "class Solution {\npublic:\n    string shortestPalindrome(string s) {\n        \n    }\n};"
      },
      {
        "lang": "Java",
        "langSlug": "java",
        "code": "class Solution {\n    public String shortestPalindrome(String s) {\n        \n    }\n}"
      },
      {
        "lang": "Python3",
        "langSlug": "python3",
        "code": "class Solution:\n    def shortestPalindrome(self, s: str) -> str:\n        "
      },
      {
        "lang": "Python",
        "langSlug": "python",
        "code": "class Solution(object):\n    def shortestPalindrome(self, s):\n        \"\"\"\n        :type s: str\n        :rtype: str\n        \"\"\"\n        "
      },
      {
        "lang": "JavaScript",
        "langSlug": "javascript",
        "code": "/**\n * @param {string} s\n * @return {string}\n */\nvar shortestPalindrome = function(s) {\n    \n};"
      },
      {
        "lang": "TypeScript",
        "langSlug": "typescript",
        "code": "function shortestPalindrome(s: string): string {\n    \n};"
      },
      {
        "lang": "C#",
        "langSlug": "csharp",
        "code": "public class Solution {\n    public string ShortestPalindrome(string s) {\n        \n    }\n}"
      },
      {
        "lang": "C",
        "langSlug": "c",
        "code": "char* shortestPalindrome(char* s) {\n    \n}"
      },
      {
        "lang": "Go",
        "langSlug": "golang",
        "code": "func shortestPalindrome(s string) string {\n    \n}"
      },
      {
        "lang": "Kotlin",
        "langSlug": "kotlin",
        "code": "class Solution {\n    fun shortestPalindrome(s: String): String {\n        \n    }\n}"
      },
      {
        "lang": "Swift",
        "langSlug": "swift",
        "code": "class Solution {\n    func shortestPalindrome(_ s: String) -> String {\n        \n    }\n}"
      },
      {
        "lang": "Rust",
        "langSlug": "rust",
        "code": "impl Solution {\n    pub fn shortest_palindrome(s: String) -> String {\n        \n    }\n}"
      },
      {
        "lang": "Ruby",
        "langSlug": "ruby",
        "code": "# @param {String} s\n# @return {String}\ndef shortest_palindrome(s)\n    \nend"
      },
      {
        "lang": "PHP",
        "langSlug": "php",
        "code": "class Solution {\n\n    /**\n     * @param String $s\n     * @return String\n     */\n    function shortestPalindrome($s) {\n        \n    }\n}"
      },
      {
        "lang": "Dart",
        "langSlug": "dart",
        "code": "class Solution {\n  String shortestPalindrome(String s) {\n    \n  }\n}"
      },
      {
        "lang": "Scala",
        "langSlug": "scala",
        "code": "object Solution {\n    def shortestPalindrome(s: String): String = {\n        \n    }\n}"
      },
      {
        "lang": "Elixir",
        "langSlug": "elixir",
        "code": "defmodule Solution do\n  @spec shortest_palindrome(s :: String.t) :: String.t\n  def shortest_palindrome(s) do\n    \n  end\nend"
      },
      {
        "lang": "Erlang",
        "langSlug": "erlang",
        "code": "-spec shortest_palindrome(S :: unicode:unicode_binary()) -> unicode:unicode_binary().\nshortest_palindrome(S) ->\n  ."
      },
      {
        "lang": "Racket",
        "langSlug": "racket",
        "code": "(define/contract (shortest-palindrome s)\n  (-> string? string?)\n  )"
      }
    ],
    "topicTags": [
      {
        "name": "String",
        "slug": "string",
        "translatedName": null
      },
      {
        "name": "Rolling Hash",
        "slug": "rolling-hash",
        "translatedName": null
      },
      {
        "name": "String Matching",
        "slug": "string-matching",
        "translatedName": null
      },
      {
        "name": "Hash Function",
        "slug": "hash-function",
        "translatedName": null
      }
    ],
    "stats": "{\"totalAccepted\": \"332.8K\", \"totalSubmission\": \"803.5K\", \"totalAcceptedRaw\": 332769, \"totalSubmissionRaw\": 803485, \"acRate\": \"41.4%\"}",
    "similarQuestions": "[{\"title\": \"Longest Palindromic Substring\", \"titleSlug\": \"longest-palindromic-substring\", \"difficulty\": \"Medium\", \"translatedTitle\": null}, {\"title\": \"Find the Index of the First Occurrence in a String\", \"titleSlug\": \"find-the-index-of-the-first-occurrence-in-a-string\", \"difficulty\": \"Easy\", \"translatedTitle\": null}, {\"title\": \"Palindrome Pairs\", \"titleSlug\": \"palindrome-pairs\", \"difficulty\": \"Hard\", \"translatedTitle\": null}, {\"title\": \"Maximum Deletions on a String\", \"titleSlug\": \"maximum-deletions-on-a-string\", \"difficulty\": \"Hard\", \"translatedTitle\": null}, {\"title\": \"Smallest Palindromic Rearrangement I\", \"titleSlug\": \"smallest-palindromic-rearrangement-i\", \"difficulty\": \"Medium\", \"translatedTitle\": null}]",
    "stats_parsed": {
      "totalAccepted": "332.8K",
      "totalSubmission": "803.5K",
      "totalAcceptedRaw": 332769,
      "totalSubmissionRaw": 803485,
      "acRate": "41.4%"
    },
    "similarQuestions_parsed": [
      {
        "title": "Longest Palindromic Substring",
        "titleSlug": "longest-palindromic-substring",
        "difficulty": "Medium",
        "translatedTitle": null
      },
      {
        "title": "Find the Index of the First Occurrence in a String",
        "titleSlug": "find-the-index-of-the-first-occurrence-in-a-string",
        "difficulty": "Easy",
        "translatedTitle": null
      },
      {
        "title": "Palindrome Pairs",
        "titleSlug": "palindrome-pairs",
        "difficulty": "Hard",
        "translatedTitle": null
      },
      {
        "title": "Maximum Deletions on a String",
        "titleSlug": "maximum-deletions-on-a-string",
        "difficulty": "Hard",
        "translatedTitle": null
      },
      {
        "title": "Smallest Palindromic Rearrangement I",
        "titleSlug": "smallest-palindromic-rearrangement-i",
        "difficulty": "Medium",
        "translatedTitle": null
      }
    ]
  },
  "discussions_preview": [],
  "fetched_at": "2025-11-25T14:57:13.678988Z"
}